dramatiq_sqs/__init__.py
dramatiq_sqs/broker.py
dramatiq_sqs_test-0.3.0.dev2.dist-info/WHEEL
dramatiq_sqs_test-0.3.0.dev2.dist-info/METADATA
dramatiq_sqs_test-0.3.0.dev2.dist-info/RECORD
