Metadata-Version: 2.4
Name: dramatiq-sqs-test
Version: 0.3.0.dev2
Summary: An Amazon SQS broker for Dramatiq.
Keywords: dramatiq,sqs
Author: Bogdan Paul Popa, Mikhail Bulash
License-Expression: Apache-2.0
Classifier: Development Status :: 3 - Alpha
Classifier: License :: OSI Approved :: Apache Software License
Classifier: Programming Language :: Python :: 3
Classifier: Programming Language :: Python :: 3.10
Classifier: Programming Language :: Python :: 3.11
Classifier: Programming Language :: Python :: 3.12
Classifier: Programming Language :: Python :: 3.13
Classifier: Programming Language :: Python :: 3.14
Classifier: Topic :: System :: Distributed Computing
Requires-Dist: boto3
Requires-Dist: dramatiq
Maintainer: Mikhail Bulash
Requires-Python: >=3.10
Project-URL: Repository, https://github.com/Bogdanp/dramatiq_sqs
